scrapy_proxyland_middleware/__init__.py
scrapy_proxyland_middleware/middleware.py
scrapy_proxyland_middleware-1.0.dist-info/LICENSE
scrapy_proxyland_middleware-1.0.dist-info/METADATA
scrapy_proxyland_middleware-1.0.dist-info/WHEEL
scrapy_proxyland_middleware-1.0.dist-info/top_level.txt
scrapy_proxyland_middleware-1.0.dist-info/RECORD
