Metadata-Version: 2.1
Name: scrapy-proxyland-middleware
Version: 1.0
Summary: Middleware to easily implement Proxyland in Scrapy projects
Home-page: UNKNOWN
Author: Patrick Klein
License: MIT
Project-URL: Source, https://github.com/patkle/scrapy-proxyland-middleware
Keywords: scrapy middleware proxy Proxyland
Platform: UNKNOWN
Classifier: Intended Audience :: Developers
Classifier: License :: OSI Approved :: MIT License
Classifier: Programming Language :: Python :: 3
Classifier: Topic :: Utilities
Requires-Python: >=3
Requires-Dist: importlib-metadata (~=1.0) ; python_version < "3.8"
